aliyunsdkcomputenestsupplier/__init__.py
aliyunsdkcomputenestsupplier/endpoint.py
aliyunsdkcomputenestsupplier/request/__init__.py
aliyunsdkcomputenestsupplier/request/v20210521/AddServiceSharedAccountsRequest.py
aliyunsdkcomputenestsupplier/request/v20210521/ContinueDeployServiceInstanceRequest.py
aliyunsdkcomputenestsupplier/request/v20210521/CreateArtifactRequest.py
aliyunsdkcomputenestsupplier/request/v20210521/CreateServiceInstanceRequest.py
aliyunsdkcomputenestsupplier/request/v20210521/CreateServiceRequest.py
aliyunsdkcomputenestsupplier/request/v20210521/DeleteArtifactRequest.py
aliyunsdkcomputenestsupplier/request/v20210521/DeleteServiceInstancesRequest.py
aliyunsdkcomputenestsupplier/request/v20210521/DeleteServiceRequest.py
aliyunsdkcomputenestsupplier/request/v20210521/DeployServiceInstanceRequest.py
aliyunsdkcomputenestsupplier/request/v20210521/GetArtifactRepositoryCredentialsRequest.py
aliyunsdkcomputenestsupplier/request/v20210521/GetArtifactRequest.py
aliyunsdkcomputenestsupplier/request/v20210521/GetServiceEstimateCostRequest.py
aliyunsdkcomputenestsupplier/request/v20210521/GetServiceInstanceRequest.py
aliyunsdkcomputenestsupplier/request/v20210521/GetServiceRequest.py
aliyunsdkcomputenestsupplier/request/v20210521/GetServiceTemplateParameterConstraintsRequest.py
aliyunsdkcomputenestsupplier/request/v20210521/GetUploadCredentialsRequest.py
aliyunsdkcomputenestsupplier/request/v20210521/ListAcrImageRepositoriesRequest.py
aliyunsdkcomputenestsupplier/request/v20210521/ListAcrImageTagsRequest.py
aliyunsdkcomputenestsupplier/request/v20210521/ListArtifactVersionsRequest.py
aliyunsdkcomputenestsupplier/request/v20210521/ListArtifactsRequest.py
aliyunsdkcomputenestsupplier/request/v20210521/ListServiceInstancesRequest.py
aliyunsdkcomputenestsupplier/request/v20210521/ListServiceUsagesRequest.py
aliyunsdkcomputenestsupplier/request/v20210521/ListServicesRequest.py
aliyunsdkcomputenestsupplier/request/v20210521/ModifyServiceInstanceResourcesRequest.py
aliyun_python_sdk_computenestsupplier-1.0.6.dist-info/LICENSE
aliyun_python_sdk_computenestsupplier-1.0.6.dist-info/METADATA
aliyun_python_sdk_computenestsupplier-1.0.6.dist-info/WHEEL
aliyun_python_sdk_computenestsupplier-1.0.6.dist-info/top_level.txt
aliyun_python_sdk_computenestsupplier-1.0.6.dist-info/RECORD
